cmdOptions/Controller.py
cmdOptions/Tools.py
cmdOptions/__init__.py
cmdoptions-0.0.5.dist-info/METADATA
cmdoptions-0.0.5.dist-info/WHEEL
cmdoptions-0.0.5.dist-info/licenses/LICENSE
cmdoptions-0.0.5.dist-info/RECORD
